README.md
setup.cfg
setup.py
pyCloudFlareUpdater/__init__.py
pyCloudFlareUpdater/__main__.py
pyCloudFlareUpdater.egg-info/PKG-INFO
pyCloudFlareUpdater.egg-info/SOURCES.txt
pyCloudFlareUpdater.egg-info/dependency_links.txt
pyCloudFlareUpdater.egg-info/entry_points.txt
pyCloudFlareUpdater.egg-info/requires.txt
pyCloudFlareUpdater.egg-info/top_level.txt
pyCloudFlareUpdater.egg-info/zip-safe
pyCloudFlareUpdater/logging_utils/__init__.py
pyCloudFlareUpdater/logging_utils/utils.py
pyCloudFlareUpdater/network/__init__.py
pyCloudFlareUpdater/network/network_utils.py
pyCloudFlareUpdater/preferences/__init__.py
pyCloudFlareUpdater/preferences/user_preferences.py
pyCloudFlareUpdater/values/__init__.py
pyCloudFlareUpdater/values/constants.py