Metadata-Version: 2.1
Name: pyCloudFlareUpdater
Version: 1.0
Summary: DDNS service for dynamically update CloudFlare 'A' Records
Home-page: https://gitlab.javinator9889.com/ddns-clients/pyCloudFlareUpdater
Author: Javinator9889
Author-email: javialonso007@hotmail.es
License: GPLv3
Download-URL: https://gitlab.javinator9889.com/ddns-clients/pyCloudFlareUpdater/repository/master/archive.zip
Platform: UNKNOWN
Classifier: Development Status :: 5 - Production/Stable
Classifier: Programming Language :: Python
Classifier: Environment :: Console
Classifier: License :: OSI Approved :: GNU General Public License v3 (GPLv3)
Classifier: Operating System :: POSIX :: Linux
Classifier: Natural Language :: English
Classifier: Programming Language :: Python :: 3
Classifier: Programming Language :: Python :: 3.1
Classifier: Programming Language :: Python :: 3.2
Classifier: Programming Language :: Python :: 3.3
Classifier: Programming Language :: Python :: 3.4
Classifier: Programming Language :: Python :: 3.5
Classifier: Programming Language :: Python :: 3.6
Classifier: Programming Language :: Python :: 3.7
